strutils/__init__.py
strutils/core.py
strutils-0.1.1.dist-info/LICENSE
strutils-0.1.1.dist-info/WHEEL
strutils-0.1.1.dist-info/METADATA
strutils-0.1.1.dist-info/RECORD
