Metadata-Version: 2.1
Name: strutils
Version: 0.1.1
Summary: Python Compound String Utilities
Home-page: https://github.com/tZ3ma/strutils
License: MIT
Keywords: python-3,compound-strings,library,tools
Author: Mathias Ammon
Author-email: mathias.ammon@tuhh.de
Requires-Python: >=3.8,<4.0
Classifier: License :: OSI Approved :: MIT License
Classifier: Programming Language :: Python :: 3
Classifier: Programming Language :: Python :: 3.8
Classifier: Programming Language :: Python :: 3.9
Classifier: Programming Language :: Python :: 3.10
Classifier: Programming Language :: Python :: 3.11
Requires-Dist: ittools (>=0.1.3,<0.2.0)
Project-URL: Repository, https://github.com/tZ3ma/strutils
